PyTSML/PyTSML.py
PyTSML/__init__.py
pytsml-1.1.dist-info/METADATA
pytsml-1.1.dist-info/WHEEL
pytsml-1.1.dist-info/licenses/LICENSE
pytsml-1.1.dist-info/RECORD
