Metadata-Version: 2.4
Name: PyTSML
Version: 1.1
Summary: Python implementations for a few machine learning algorithms used for working with time series, including LDMLT and DDE
Project-URL: Homepage, https://github.com/Bl0tniaQus/PyTSML
Project-URL: Issues, https://github.com/Bl0tniaQus/PyTSML/issues
Author-email: Adrian Hałys <bl0tniaqus578@gmail.com>
License-Expression: Apache-2.0
License-File: LICENSE
Keywords: Classification,DDE,DE,DTW,Delay Embedding,LDMLT,Machine Learning,Time Series
Classifier: Operating System :: OS Independent
Classifier: Programming Language :: Python :: 3
Requires-Python: >=3.11
Requires-Dist: fastdtw>=0.3.4
Requires-Dist: scipy>=1.14.1
